bps_restpy/__init__.py
bps_restpy/bps.py
bps_restpy/bpsVELicense.py
bps_restpy/restPyWrapper.py
bps_restpy/restPyWrapper3.py
bps_restpy/bps_restpy_admin/__init__.py
bps_restpy/bps_restpy_admin/bpsAdminRest.py
bps_restpy/bps_restpy_admin/bpsRest.py
bps_restpy/bps_restpy_admin/bpsVEAdminRest.py
bps_restpy/bps_restpy_admin/restv1_samples/sample_bpsadmin_restore.py
bps_restpy/bps_restpy_admin/restv1_samples/sample_bpsadmin_update.py
bps_restpy/bps_restpy_admin/restv1_samples/sample_bpsveadmin_addslot.py
bps_restpy/bps_restpy_admin/restv1_samples/sample_script.py
bps_restpy/rest_samples/Sample_AppSim_template.bpt
bps_restpy/rest_samples/nn_sample.bpt
bps_restpy/rest_samples/s01_New_Reserve_Run.py
bps_restpy/rest_samples/s02_Load_Configure_Run_Report.py
bps_restpy/rest_samples/s03_Flow_SuperFlow_AppProfile.py
bps_restpy/rest_samples/s04_Configure_Network.py
bps_restpy/rest_samples/s05_RunCancel_EvaluateReport_and_ExportCapture.py
bps_restpy/rest_samples/s06_StrikeLists_and_Strikes.py
bps_restpy/rest_samples/s07_TestModel_Run.py
bps_restpy/rest_samples/s08_StrikeEvasionsResultParse.py
bps_restpy/rest_samples/s09_Topology_LoadModuleOperations.py
bps_restpy/rest_samples/s10_BPSVE_Manage_License.py
bps_restpy/rest_samples/s11_aps400_bit_blaster.py
bps_restpy/rest_samples/s12_aps400_layer3.py
bps_restpy/rest_samples/s13_aps400_appsim.py
bps_restpy/rest_samples/s14_CS_AppSim_fanout.py
bps_restpy/rest_samples/s15_aps400_AppSim_fanout.py
bps_restpy-11.0.0.dist-info/LICENSE
bps_restpy-11.0.0.dist-info/METADATA
bps_restpy-11.0.0.dist-info/WHEEL
bps_restpy-11.0.0.dist-info/top_level.txt
bps_restpy-11.0.0.dist-info/RECORD
