Metadata-Version: 2.1
Name: bps-restpy
Version: 11.0.0
Summary: BreakingPoint REST API Python Wraper
Home-page: https://github.com/OpenIxia/bps_restpy
Author: Keysight ISG BreakingPoint Team
Author-email: constantin.cretu@keysight.com
License: MIT
Keywords: bps breakingpoint security network test tool ixia keysight automation
Classifier: Development Status :: 5 - Production/Stable
Classifier: Intended Audience :: Developers
Classifier: Topic :: Software Development
Classifier: License :: OSI Approved :: MIT License
Classifier: Programming Language :: Python :: 2.7
Classifier: Programming Language :: Python :: 3
Requires-Python: >=2.7, <4
License-File: LICENSE
Requires-Dist: requests
